libp2p_kit_py/__init__.py
libp2p_kit_py/main.py
libp2p_kit_py/aria2_kit/__init__.py
libp2p_kit_py/aria2_kit/aria2_kit.py
libp2p_kit_py/libp2p_kit/__init__.py
libp2p_kit_py/libp2p_kit/libp2p.py
libp2p_kit_py/s3_kit/__init__.py
libp2p_kit_py/s3_kit/s3_kit.py
libp2p_kit_py/websocket_kit/__init__.py
libp2p_kit_py/websocket_kit/websocket_kit.py
libp2p_kit_py/websocket_kit/websocket_kit_lib.py
test/__init__.py
test/test.py
libp2p_kit_py-0.0.19.dist-info/METADATA
libp2p_kit_py-0.0.19.dist-info/WHEEL
libp2p_kit_py-0.0.19.dist-info/top_level.txt
libp2p_kit_py-0.0.19.dist-info/RECORD
